chcldemo/ConstructHW.py
chcldemo/DataProcess.py
chcldemo/DataSet.py
chcldemo/HypergraphConstructKNN.py
chcldemo/HypergraphConstructKmeans.py
chcldemo/Module.py
chcldemo/__init__.py
chcldemo/chcldemo.py
chcldemo/param.py
chcldemo/trainer.py
chcldemo/utils.py
chcldemo-0.0.4.dist-info/LICENSE
chcldemo-0.0.4.dist-info/METADATA
chcldemo-0.0.4.dist-info/WHEEL
chcldemo-0.0.4.dist-info/top_level.txt
chcldemo-0.0.4.dist-info/RECORD
