Metadata-Version: 2.1
Name: chcldemo
Version: 0.0.4
Summary: Hypergraph contrastive learning framework for multiple similarity modalities
Home-page: https://github.com/test/test.git
Author: Chen
Author-email: <example@example.com>
Keywords: Multiple Similarity Modes,MHGCL,Hypergraph Contrastive Learning
Classifier: Development Status :: 1 - Planning
Classifier: Intended Audience :: Developers
Classifier: Programming Language :: Python :: 3
Classifier: Operating System :: Unix
Classifier: Operating System :: MacOS :: MacOS X
Classifier: Operating System :: Microsoft :: Windows
License-File: LICENSE
Requires-Dist: numpy<2.0,>=1.22.4
Requires-Dist: pandas>=2.2.3
Requires-Dist: scikit-learn>=1.5.2
Requires-Dist: scipy>=1.13.1
Requires-Dist: torch>=1.10.0
Requires-Dist: joblib>=1.4.2
